wharve/__init__.py
wharve-0.1.0.dist-info/LICENSE
wharve-0.1.0.dist-info/METADATA
wharve-0.1.0.dist-info/WHEEL
wharve-0.1.0.dist-info/RECORD
